{"blocks_bookmark.md":"19720cc1","blocks_breadcrumb.md":"30ed55f2","blocks_bulletedlistitem.md":"c09eeac1","blocks_callout.md":"191e89c6","blocks_childdatabase.md":"28842e64","blocks_childpage.md":"ff4dc4f5","blocks_code.md":"0cf47a58","blocks_column.md":"48add9d5","blocks_columnlist.md":"85bb4d28","blocks_divider.md":"a6f20b56","blocks_embed.md":"641c1577","blocks_equationblock.md":"039bb44b","blocks_fileblock.md":"076e2e2b","blocks_heading.md":"c67b6825","blocks_image.md":"19fd387f","blocks_linkpreview.md":"ea83f1ba","blocks_numberedlistitem.md":"ebed6dcc","blocks_paragraph.md":"3255c10e","blocks_pdf.md":"7c4a4955","blocks_quote.md":"d60d77bd","blocks_index.md":"0e7044aa","getting-started.md":"139addd9","how-to_add-content-to-page.md":"a6c1350f","how-to_add-row-to-database.md":"2aa3806c","how-to_create-a-page.md":"dfac74d0","how-to_delete-a-page.md":"1503c51f","how-to_find-a-page.md":"dd5c3b15","how-to_list-database-pages.md":"2dd918db","how-to_query-database.md":"3ff2116d","how-to_update-a-page.md":"6062d2c6","index.md":"ce877979"}
