{"advanced_configuration.md":"a946b66c","blocks_bookmark.md":"ef0051bd","blocks_breadcrumb.md":"eb8c4d43","blocks_bulletedlistitem.md":"796ba885","blocks_callout.md":"31ffc52b","blocks_childdatabase.md":"0990113e","blocks_childpage.md":"6425dfa1","blocks_code.md":"ad202548","blocks_column.md":"877f61a5","blocks_columnlist.md":"26be43c5","blocks_divider.md":"b69b1c9f","blocks_embed.md":"45b97723","blocks_equationblock.md":"587c7541","blocks_fileblock.md":"c56446f0","blocks_heading.md":"284b1094","blocks_image.md":"2ae134d9","blocks_linkpreview.md":"f779db4d","blocks_numberedlistitem.md":"e494b348","blocks_paragraph.md":"b7a0f6a4","blocks_pdf.md":"b5b1852f","blocks_quote.md":"87e09ae2","blocks_index.md":"a41dfdcb","comments_index.md":"cad3dbfa","getting-started.md":"d7682acc","how-to_add-content-to-page.md":"33a102f7","how-to_add-row-to-database.md":"93fcc15a","how-to_create-a-page.md":"7cfb4fed","how-to_delete-a-page.md":"760b0623","how-to_find-a-page.md":"7b362f94","how-to_list-database-pages.md":"cad432c1","how-to_query-database.md":"9c41c66e","how-to_update-a-page.md":"d0cfa77b","index.md":"4575556c","page-properties_people.md":"391c6fee","page-properties_index.md":"6fb3badb","search_index.md":"5ca603b1"}
