{"advanced_configuration.md":"13278e31","blocks_bookmark.md":"4d8f6df5","blocks_breadcrumb.md":"618fcd60","blocks_bulletedlistitem.md":"21f2f5da","blocks_callout.md":"fa2c3add","blocks_childdatabase.md":"a5cb8902","blocks_childpage.md":"f935b060","blocks_code.md":"b775768f","blocks_column.md":"31cc93b6","blocks_columnlist.md":"fde50870","blocks_divider.md":"9847cfe9","blocks_embed.md":"518e1b0d","blocks_equationblock.md":"0dab6a77","blocks_fileblock.md":"6231bbf0","blocks_heading.md":"f635b96c","blocks_image.md":"e086276e","blocks_linkpreview.md":"233dbe94","blocks_numberedlistitem.md":"b4420b5a","blocks_paragraph.md":"893f5d9c","blocks_pdf.md":"d42310e6","blocks_quote.md":"e4eb8d70","blocks_index.md":"997f2048","comments_index.md":"e8cb45df","getting-started.md":"360445bf","how-to_add-content-to-page.md":"e8722192","how-to_add-row-to-database.md":"6c3f013c","how-to_create-a-page.md":"379bcb6b","how-to_delete-a-page.md":"d65c7931","how-to_find-a-page.md":"cc96750e","how-to_list-database-pages.md":"46317e7a","how-to_query-database.md":"69fd066a","how-to_update-a-page.md":"d71c8ec9","index.md":"b2808683","page-properties_people.md":"7e2e2ad2","page-properties_index.md":"94b148de","search_index.md":"4d55e558"}
