{"advanced_configuration.md":"c9c1c30c","blocks_bookmark.md":"4ee80a72","blocks_breadcrumb.md":"d38f21b5","blocks_bulletedlistitem.md":"731b2305","blocks_callout.md":"cbc5a645","blocks_childdatabase.md":"52f31a2e","blocks_childpage.md":"0870ec68","blocks_code.md":"c0af1cc2","blocks_column.md":"5936c6e8","blocks_columnlist.md":"81dfb60b","blocks_divider.md":"0761615c","blocks_embed.md":"74b6c530","blocks_equationblock.md":"d2e38172","blocks_fileblock.md":"6614aa3c","blocks_heading.md":"f0bcc94b","blocks_image.md":"20adcb4a","blocks_linkpreview.md":"b364c6b5","blocks_numberedlistitem.md":"78514a30","blocks_paragraph.md":"9f337dc8","blocks_pdf.md":"7de2e136","blocks_quote.md":"18f3a679","blocks_index.md":"a3a91759","comments_index.md":"de1cbe93","getting-started.md":"f3c4c9eb","how-to_add-content-to-page.md":"cc2f7629","how-to_add-row-to-database.md":"1fc6e21f","how-to_create-a-page.md":"679ca032","how-to_delete-a-page.md":"6f632e73","how-to_find-a-page.md":"addfb714","how-to_list-database-pages.md":"0c872db3","how-to_query-database.md":"1a608a78","how-to_update-a-page.md":"0e563bda","index.md":"a022f796","page-properties_people.md":"964f1086","page-properties_index.md":"7c4ebbf7","search_index.md":"76b1e10c"}
